{"last_run":"2026-03-18","run_id":"23265486972","fv_tool":"Lean4+Mathlib","lake_project":"formal-verification/lean/","targets":[{"id":"vote_result","phase":3,"lean_file":"formal-verification/lean/FVSquad/MajorityQuorum.lean","notes":"Lean spec done. 11 theorems proved (no sorry). PR: lean-squad/lean-spec-majority-quorum. Next: Task4."},{"id":"committed_index","phase":2,"informal_spec":"formal-verification/specs/committed_index_informal.md","notes":"Informal spec done. PR same. Next: Task3 Lean spec."},{"id":"limit_size","phase":1},{"id":"unstable_log","phase":1},{"id":"inflights","phase":1}],"next_steps":["Task4: Lean impl for vote_result","Task3: Lean spec for committed_index","Task6: verify lake build"],"build_note":"lake build not verified - network firewall blocks elan"}
